{
	"clazz": [
		{
			"amount": 248620352212.60,
			"name": "Liquidity and Money",
			"weight": 63.83,
			"currency": "GBP",
			"nodes": [
				{
					"amount": 124310176106.3,
					"name": "Futures on Forex",
					"currency": "GBP",
					"weight": 50
				},
				{
					"amount": 124310176106.3,
					"name": "Mutual Funds Money Market",
					"currency": "GBP",
					"weight": 50
				}
			]
		},
		{
			"amount": 123355891502.00,
			"name": "Hedge Funds",
			"weight": 31.67,
			"currency": "GBP",
			"nodes": [
				{
					"amount": 79959288871.60,
					"name": "Hedge Funds",
					"currency": "GBP",
					"weight": 64.82
				},
				{
					"amount": 43396602630.40,
					"name": "Hedge Funds (Islamic Products)",
					"currency": "GBP",
					"weight": 35.18
				}
			]
		},
		{
			"amount": 49622799423.29,
			"name": "Commodities",
			"weight": 12.74,
			"currency": "GBP",
			"nodes": [
				{
					"amount": 36194869899.35,
					"name": "Commodity Linked OTC Derivatives",
					"currency": "GBP",
					"weight": 72.94
				},
				{
					"amount": 13427929523.94,
					"name": "Commodity Funds",
					"currency": "GBP",
					"weight": 27.06
				}
			]
		},
		{
			"amount": 9500000001.29,
			"name": "Real Estate",
			"weight": 12.74,
			"currency": "GBP",
			"nodes": [
				{
					"amount": 5000000000.35,
					"name": "Real Estate 1",
					"currency": "GBP",
					"weight": 47.37
				},
				{
					"amount": 4500000000.94,
					"name": "Real Estate 2",
					"currency": "GBP",
					"weight": 52.63
				}
			]
		},
		{
			"amount": 1280000000.44,
			"name": "Liabilities",
			"weight": 8.96,
			"currency": "GBP",
			"nodes": [
				{
					"amount": 720000000.32,
					"name": "Liabilities 1",
					"currency": "GBP",
					"weight": 56.25
				},
				{
					"amount": 560000000.12,
					"name": "Liabilities 2",
					"currency": "GBP",
					"weight": 43.75
				}

			]
		}
	],
	"currency": [
		{
			"amount": 116266920155.82,
			"name": "Hong Kong Dollar",
			"currency": "GBP",
			"weight": 29.85
		},
		{
			"amount": 76615421087.60,
			"name": "US Dollar",
			"currency": "GBP",
			"weight": 19.67
		},
		{
			"amount": 65202956228.09,
			"name": "Australian Dollar",
			"currency": "GBP",
			"weight": 16.74
		},
		{
			"amount": 41754820236.86,
			"name": "Canadian Dollar",
			"currency": "GBP",
			"weight": 10.72
		},
		{
			"amount": 41754820236.86,
			"name": "Japanese Yen",
			"currency": "GBP",
			"weight": 10.72
		},
		{
			"amount": 16904470133.21,
			"name": "Singapore Dollar",
			"currency": "GBP",
			"weight": 4.3
		},
		{
			"amount": 15375154097,
			"name": "Thai Baht",
			"currency": "GBP",
			"weight": 4
		}
	],
	"region": [
		{
			"amount": 112177128994,
			"name": "Europe",
			"currency": "GBP",
			"weight": 29
		},
		{
			"amount": 84911854586.16,
			"name": "Asia",
			"currency": "GBP",
			"weight": 21.8
		},
		{
			"amount": 57257076257.64,
			"name": "North America",
			"currency": "GBP",
			"weight": 14.7
		},
		{
			"amount": 33497337130.32,
			"name": "Latin America",
			"currency": "GBP",
			"weight": 8.6
		},
		{
			"amount": 30498156945.40,
			"name": "Australia",
			"currency": "GBP",
			"weight": 7.83
		},
		{
			"amount": 30498156945.40,
			"name": "Canada",
			"currency": "GBP",
			"weight": 7.83
		}
	]
}

